alipay_zxw/__init__.py
alipay_zxw/compat.py
alipay_zxw/exceptions.py
alipay_zxw/loggers.py
alipay_zxw/pay_async.py
alipay_zxw/utils.py
alipay_zxw-0.0.4.dist-info/METADATA
alipay_zxw-0.0.4.dist-info/WHEEL
alipay_zxw-0.0.4.dist-info/top_level.txt
alipay_zxw-0.0.4.dist-info/RECORD
